bbconf/__init__.py
bbconf/_version.py
bbconf/bbagent.py
bbconf/const.py
bbconf/db_utils.py
bbconf/exceptions.py
bbconf/helpers.py
bbconf/config_parser/__init__.py
bbconf/config_parser/bedbaseconfig.py
bbconf/config_parser/const.py
bbconf/config_parser/models.py
bbconf/config_parser/utils.py
bbconf/models/__init__.py
bbconf/models/base_models.py
bbconf/models/bed_models.py
bbconf/models/bedset_models.py
bbconf/models/drs_models.py
bbconf/modules/__init__.py
bbconf/modules/bedfiles.py
bbconf/modules/bedsets.py
bbconf/modules/objects.py
bbconf/utils/usage_events.csv
bbconf-0.14.3.dist-info/licenses/LICENSE.txt
bbconf-0.14.3.dist-info/METADATA
bbconf-0.14.3.dist-info/WHEEL
bbconf-0.14.3.dist-info/top_level.txt
bbconf-0.14.3.dist-info/RECORD
