Metadata-Version: 2.4
Name: bbconf
Version: 0.14.3
Summary: Configuration package for bedbase project
Home-page: https://databio.org
Author: Michal Stolarczyk, Oleksandr Khoroshevskyi
Author-email: khorosh@virginia.edu
License: BSD2
Classifier: Development Status :: 4 - Beta
Classifier: License :: OSI Approved :: BSD License
Classifier: Programming Language :: Python :: 3.10
Classifier: Programming Language :: Python :: 3.11
Classifier: Programming Language :: Python :: 3.12
Classifier: Programming Language :: Python :: 3.13
Classifier: Topic :: Scientific/Engineering :: Bio-Informatics
License-File: LICENSE.txt
Requires-Dist: yacman>=0.9.1
Requires-Dist: sqlalchemy>=2.0.0
Requires-Dist: gtars>=0.5.3
Requires-Dist: geniml[ml]>=0.8.4
Requires-Dist: psycopg>=3.1.15
Requires-Dist: coloredlogs
Requires-Dist: pydantic>=2.9.0
Requires-Dist: botocore<1.36.0,>=1.34.0
Requires-Dist: boto3<1.36.0,>=1.34.54
Requires-Dist: pephubclient>=0.4.5
Requires-Dist: sqlalchemy_schemadisplay
Requires-Dist: zarr<3.0.0
Requires-Dist: pyyaml>=6.0.1
Requires-Dist: s3fs>=2024.3.1
Requires-Dist: pandas>=2.0.0
Requires-Dist: pybiocfilecache==0.6.1
Requires-Dist: umap-learn>=0.5.8
Requires-Dist: qdrant_client>=1.16.1
Dynamic: author
Dynamic: author-email
Dynamic: classifier
Dynamic: description
Dynamic: description-content-type
Dynamic: home-page
Dynamic: keywords
Dynamic: license
Dynamic: license-file
Dynamic: requires-dist
Dynamic: summary
